coingecko_scrape_data/__init__.py
coingecko_scrape_data/coin_data.py
coingecko_scrape_data-1.0.1.dist-info/License.txt
coingecko_scrape_data-1.0.1.dist-info/METADATA
coingecko_scrape_data-1.0.1.dist-info/WHEEL
coingecko_scrape_data-1.0.1.dist-info/top_level.txt
coingecko_scrape_data-1.0.1.dist-info/RECORD
