Metadata-Version: 2.1
Name: coingecko-scrape-data
Version: 1.0.1
Summary: coingecko scraper
Home-page: UNKNOWN
Author: DataKund
Author-email: datakund@gmail.com
License: Apache License 2.0
Keywords: A python library to scrape coin detail of the  link provided
Platform: UNKNOWN
License-File: License.txt
Requires-Dist: datakund-cloud
